fab_coreui_theme/__init__.py
fab_coreui_theme/_version.py
fab_coreui_theme/fab_coreui_theme.py
fab_coreui_theme/static/coreui/assets/brand/coreui.svg
fab_coreui_theme/static/coreui/assets/favicon/android-icon-144x144.png
fab_coreui_theme/static/coreui/assets/favicon/android-icon-192x192.png
fab_coreui_theme/static/coreui/assets/favicon/android-icon-36x36.png
fab_coreui_theme/static/coreui/assets/favicon/android-icon-48x48.png
fab_coreui_theme/static/coreui/assets/favicon/android-icon-72x72.png
fab_coreui_theme/static/coreui/assets/favicon/android-icon-96x96.png
fab_coreui_theme/static/coreui/assets/favicon/apple-icon-114x114.png
fab_coreui_theme/static/coreui/assets/favicon/apple-icon-120x120.png
fab_coreui_theme/static/coreui/assets/favicon/apple-icon-144x144.png
fab_coreui_theme/static/coreui/assets/favicon/apple-icon-152x152.png
fab_coreui_theme/static/coreui/assets/favicon/apple-icon-180x180.png
fab_coreui_theme/static/coreui/assets/favicon/apple-icon-57x57.png
fab_coreui_theme/static/coreui/assets/favicon/apple-icon-60x60.png
fab_coreui_theme/static/coreui/assets/favicon/apple-icon-72x72.png
fab_coreui_theme/static/coreui/assets/favicon/apple-icon-76x76.png
fab_coreui_theme/static/coreui/assets/favicon/apple-icon-precomposed.png
fab_coreui_theme/static/coreui/assets/favicon/apple-icon.png
fab_coreui_theme/static/coreui/assets/favicon/browserconfig.xml
fab_coreui_theme/static/coreui/assets/favicon/favicon-16x16.png
fab_coreui_theme/static/coreui/assets/favicon/favicon-32x32.png
fab_coreui_theme/static/coreui/assets/favicon/favicon-96x96.png
fab_coreui_theme/static/coreui/assets/favicon/favicon.ico
fab_coreui_theme/static/coreui/assets/favicon/manifest.json
fab_coreui_theme/static/coreui/assets/favicon/ms-icon-144x144.png
fab_coreui_theme/static/coreui/assets/favicon/ms-icon-150x150.png
fab_coreui_theme/static/coreui/assets/favicon/ms-icon-310x310.png
fab_coreui_theme/static/coreui/assets/favicon/ms-icon-70x70.png
fab_coreui_theme-0.12.0.dist-info/AUTHORS.rst
fab_coreui_theme-0.12.0.dist-info/LICENSE
fab_coreui_theme-0.12.0.dist-info/METADATA
fab_coreui_theme-0.12.0.dist-info/WHEEL
fab_coreui_theme-0.12.0.dist-info/top_level.txt
fab_coreui_theme-0.12.0.dist-info/RECORD
