Metadata-Version: 2.1
Name: fab_coreui_theme
Version: 0.12.0
Summary: CoreUI theme for FlaskAppbuilder
Home-page: https://github.com/Dabble-of-DevOps-BioHub/fab_coreui_theme
Author: Jillian Rowe
Author-email: jillian@dabbleofdevops.com
License: MIT license
Keywords: fab_coreui_theme
Platform: UNKNOWN
Classifier: Development Status :: 2 - Pre-Alpha
Classifier: Intended Audience :: Developers
Classifier: License :: OSI Approved :: MIT License
Classifier: Natural Language :: English
Classifier: Programming Language :: Python :: 3
Classifier: Programming Language :: Python :: 3.6
Classifier: Programming Language :: Python :: 3.7
Classifier: Programming Language :: Python :: 3.8
Requires-Python: >=3.6
License-File: LICENSE
License-File: AUTHORS.rst
